MANIFEST.in
README.md
setup.py
eyesight_tools/__init__.py
eyesight_tools/config.cpython-36m-x86_64-linux-gnu.so
eyesight_tools/draw_tools.cpython-36m-x86_64-linux-gnu.so
eyesight_tools/face_align_tools.cpython-36m-x86_64-linux-gnu.so
eyesight_tools/face_bank_tools.cpython-36m-x86_64-linux-gnu.so
eyesight_tools/file_tools.cpython-36m-x86_64-linux-gnu.so
eyesight_tools/generate_tools.cpython-36m-x86_64-linux-gnu.so
eyesight_tools/json_encoder.cpython-36m-x86_64-linux-gnu.so
eyesight_tools/license_tools.cpython-36m-x86_64-linux-gnu.so
eyesight_tools/logger_tools.cpython-36m-x86_64-linux-gnu.so
eyesight_tools/option.cpython-36m-x86_64-linux-gnu.so
eyesight_tools/rows_count_tools.cpython-36m-x86_64-linux-gnu.so
eyesight_tools/task_tools.cpython-36m-x86_64-linux-gnu.so
eyesight_tools/time_tools.cpython-36m-x86_64-linux-gnu.so
eyesight_tools.egg-info/PKG-INFO
eyesight_tools.egg-info/SOURCES.txt
eyesight_tools.egg-info/dependency_links.txt
eyesight_tools.egg-info/requires.txt
eyesight_tools.egg-info/top_level.txt