Metadata-Version: 1.0
Name: eyesight-tools
Version: 0.0.1
Summary: eyesight 相关工具类封装
Home-page: UNKNOWN
Author: gm
Author-email: 1025304567@qq.com
License: MIT Licence
Keywords: pip,eyesight,eyesight_tools,tool,gm
Platform: any
